{"fpsum": {"oth": {"bankdeptot": -24658, "creditor": 284599, "pay": 0, "recpt": 75827, "cashtot": 216090, "debitor": 267495}, "sale": {"salebilcount": 621, "salehigh": 11660, "returncount": 0, "salecash": 0, "salereturn": 0, "pcount": 80, "salecredit": 0, "saletot": 671588, "month": {"FEBRUARY": 45190, "OCTOBER": 47798, "MARCH": 78186, "AUGUST": 65054, "SEPTEMBER": 54659, "DECEMBER": 48175, "JUNE": 53110, "APRIL": 53255, "JANUARY": 45145, "MAY": 59324, "JULY": 56502, "NOVEMBER": 65190}}, "pur": {"purbilcount": 45, "purtot": 409426.0, "purcash": 0, "purreturn": 0, "pcount": 10, "purcredit": 0, "returncount": 0, "purhigh": 28985, "month": {"FEBRUARY": 30082, "OCTOBER": 26994, "MARCH": 60003, "AUGUST": 47852, "SEPTEMBER": 48956, "DECEMBER": 18078, "JUNE": 50178, "APRIL": 11633, "JANUARY": 26007, "MAY": 40988, "JULY": 0, "NOVEMBER": 48655}}}}